realtimemix/__init__.py
realtimemix/buffer.py
realtimemix/engine.py
realtimemix/processor.py
realtimemix/py.typed
realtimemix/streaming.py
realtimemix/utils.py
realtimemix-1.4.0.dist-info/licenses/LICENSE
realtimemix-1.4.0.dist-info/METADATA
realtimemix-1.4.0.dist-info/WHEEL
realtimemix-1.4.0.dist-info/top_level.txt
realtimemix-1.4.0.dist-info/RECORD
