Metadata-Version: 2.4
Name: realtimemix
Version: 1.4.0
Summary: A high-performance real-time audio mixing engine for Python
Author-email: Birch Kwok <birchkwok@gmail.com>
Maintainer-email: Birch Kwok <birchkwok@gmail.com>
License: MIT
Project-URL: Homepage, https://github.com/birchkwok/realtimemix
Project-URL: Documentation, https://github.com/birchkwok/realtimemix#readme
Project-URL: Repository, https://github.com/birchkwok/realtimemix.git
Project-URL: Bug Tracker, https://github.com/birchkwok/realtimemix/issues
Keywords: audio,mixer,real-time,sounddevice,numpy
Classifier: Development Status :: 5 - Production/Stable
Classifier: Intended Audience :: Developers
Classifier: License :: OSI Approved :: MIT License
Classifier: Operating System :: OS Independent
Classifier: Programming Language :: Python :: 3
Classifier: Programming Language :: Python :: 3.9
Classifier: Programming Language :: Python :: 3.10
Classifier: Programming Language :: Python :: 3.11
Classifier: Programming Language :: Python :: 3.12
Classifier: Topic :: Multimedia :: Sound/Audio
Classifier: Topic :: Multimedia :: Sound/Audio :: Mixers
Classifier: Topic :: Software Development :: Libraries :: Python Modules
Requires-Python: >=3.9
License-File: LICENSE
Requires-Dist: numpy>=1.19.0
Requires-Dist: sounddevice>=0.4.0
Requires-Dist: soundfile>=0.10.0
Provides-Extra: high-quality
Requires-Dist: librosa>=0.8.0; extra == "high-quality"
Requires-Dist: scipy>=1.7.0; extra == "high-quality"
Provides-Extra: time-stretch
Requires-Dist: pyrubberband>=0.3.0; extra == "time-stretch"
Provides-Extra: all
Requires-Dist: librosa>=0.8.0; extra == "all"
Requires-Dist: scipy>=1.7.0; extra == "all"
Requires-Dist: pyrubberband>=0.3.0; extra == "all"
Provides-Extra: dev
Requires-Dist: pytest>=6.0; extra == "dev"
Requires-Dist: pytest-cov; extra == "dev"
Requires-Dist: black; extra == "dev"
Requires-Dist: flake8; extra == "dev"
Requires-Dist: mypy; extra == "dev"
Requires-Dist: pre-commit; extra == "dev"
Dynamic: license-file
